mdbook_pdf_outline/__init__.py
mdbook_pdf_outline/mdbook_pdf_outline.py
mdbook_pdf_outline-0.1.6.dist-info/LICENSE
mdbook_pdf_outline-0.1.6.dist-info/METADATA
mdbook_pdf_outline-0.1.6.dist-info/WHEEL
mdbook_pdf_outline-0.1.6.dist-info/entry_points.txt
mdbook_pdf_outline-0.1.6.dist-info/top_level.txt
mdbook_pdf_outline-0.1.6.dist-info/RECORD
