Metadata-Version: 2.2
Name: mdbook-pdf-outline
Version: 0.1.6
Summary: Tool for generating outlines for PDF files generated by mdbook-pdf.
Home-page: https://github.com/HollowMan6/mdbook-pdf
Author: Hollow Man (Domain Address)
Author-email: hollowman@opensuse.org
License: GPL-3.0-or-later
Project-URL: Bug Tracker, https://github.com/HollowMan6/mdbook-pdf/issues
Classifier: Programming Language :: Python :: 3
Classifier: License :: OSI Approved :: GNU General Public License v3 or later (GPLv3+)
Classifier: Topic :: Text Processing :: Markup :: Markdown
License-File: LICENSE
Requires-Dist: lxml
Requires-Dist: pypdf
Dynamic: author
Dynamic: author-email
Dynamic: classifier
Dynamic: description
Dynamic: description-content-type
Dynamic: home-page
Dynamic: license
Dynamic: project-url
Dynamic: requires-dist
Dynamic: summary
